pymetis-2025.2.2.dist-info/RECORD
pymetis-2025.2.2.dist-info/WHEEL
pymetis-2025.2.2.dist-info/METADATA
pymetis/version.py
pymetis/_internal.cpython-311-darwin.so
pymetis/__init__.py
pymetis/_internal.pyi
pymetis/py.typed
