Metadata-Version: 2.4
Name: pymetis
Version: 2025.2.2
Summary: A graph partitioning package
Author-Email: Andreas Kloeckner <inform@tiker.net>
Maintainer-Email: Andreas Kloeckner <inform@tiker.net>
License-Expression: MIT AND Apache-2.0
Classifier: Development Status :: 4 - Beta
Classifier: Intended Audience :: Developers
Classifier: Intended Audience :: Other Audience
Classifier: Intended Audience :: Science/Research
Classifier: Natural Language :: English
Classifier: Programming Language :: C
Classifier: Programming Language :: C++
Classifier: Programming Language :: Python
Classifier: Programming Language :: Python :: 3 :: Only
Classifier: Topic :: Multimedia :: Graphics :: 3D Modeling
Classifier: Topic :: Scientific/Engineering
Classifier: Topic :: Scientific/Engineering :: Mathematics
Classifier: Topic :: Scientific/Engineering :: Visualization
Classifier: Topic :: Software Development :: Libraries
Project-URL: Documentation, https://documen.tician.de/pymetis
Project-URL: Repository, https://github.com/inducer/pymetis
Requires-Python: >=3.10
Requires-Dist: typing-extensions>=4.5
Provides-Extra: doc
Requires-Dist: furo; extra == "doc"
Requires-Dist: sphinx>=4; extra == "doc"
Requires-Dist: sphinx-copybutton; extra == "doc"
Provides-Extra: test
Requires-Dist: numpy; extra == "test"
Requires-Dist: meshpy; extra == "test"
Requires-Dist: pytest; extra == "test"
Requires-Dist: ruff; extra == "test"
Requires-Dist: typos; extra == "test"
